qtrangeslider/__init__.py
qtrangeslider/_generic_range_slider.py
qtrangeslider/_generic_slider.py
qtrangeslider/_labeled.py
qtrangeslider/_range_style.py
qtrangeslider/_sliders.py
qtrangeslider/_version.py
qtrangeslider/_tests/__init__.py
qtrangeslider/_tests/_testutil.py
qtrangeslider/_tests/test_float.py
qtrangeslider/_tests/test_generic_slider.py
qtrangeslider/_tests/test_range_slider.py
qtrangeslider/_tests/test_single_value_sliders.py
qtrangeslider/_tests/test_slider.py
qtrangeslider/qtcompat/QtCore.py
qtrangeslider/qtcompat/QtGui.py
qtrangeslider/qtcompat/QtWidgets.py
qtrangeslider/qtcompat/__init__.py
QtRangeSlider-0.1.5.dist-info/LICENSE
QtRangeSlider-0.1.5.dist-info/METADATA
QtRangeSlider-0.1.5.dist-info/WHEEL
QtRangeSlider-0.1.5.dist-info/top_level.txt
QtRangeSlider-0.1.5.dist-info/RECORD
