Metadata-Version: 2.1
Name: QtRangeSlider
Version: 0.1.5
Summary: Multi-handle range slider widget for PyQt/PySide
Home-page: https://github.com/tlambert03/QtRangeSlider
Author: Talley Lambert
Author-email: talley.lambert@gmail.com
License: BSD-3
Project-URL: Source, https://github.com/tlambert03/QtRangeSlider
Project-URL: Tracker, https://github.com/tlambert03/QtRangeSlider/issues
Project-URL: Changelog, https://github.com/tlambert03/QtRangeSlider/blob/master/CHANGELOG.md
Keywords: qt,range slider,widget
Platform: UNKNOWN
Classifier: Development Status :: 4 - Beta
Classifier: Environment :: X11 Applications :: Qt
Classifier: Intended Audience :: Developers
Classifier: License :: OSI Approved :: BSD License
Classifier: Operating System :: OS Independent
Classifier: Programming Language :: Python
Classifier: Programming Language :: Python :: 3 :: Only
Classifier: Programming Language :: Python :: 3.6
Classifier: Programming Language :: Python :: 3.7
Classifier: Programming Language :: Python :: 3.8
Classifier: Programming Language :: Python :: 3.9
Classifier: Topic :: Desktop Environment
Classifier: Topic :: Software Development
Classifier: Topic :: Software Development :: User Interfaces
Classifier: Topic :: Software Development :: Widget Sets
Requires-Python: >=3.6
License-File: LICENSE
Provides-Extra: dev
Requires-Dist: ipython ; extra == 'dev'
Requires-Dist: jedi (<0.18.0) ; extra == 'dev'
Requires-Dist: isort ; extra == 'dev'
Requires-Dist: mypy ; extra == 'dev'
Requires-Dist: pre-commit ; extra == 'dev'
Requires-Dist: tox ; extra == 'dev'
Requires-Dist: tox-conda ; extra == 'dev'
Requires-Dist: pytest ; extra == 'dev'
Requires-Dist: pytest-qt ; extra == 'dev'
Requires-Dist: pytest-cov ; extra == 'dev'
Requires-Dist: pyqt5 ; extra == 'dev'
Provides-Extra: pyqt5
Requires-Dist: pyqt5 ; extra == 'pyqt5'
Provides-Extra: pyqt6
Requires-Dist: pyqt6 ; extra == 'pyqt6'
Provides-Extra: pyside2
Requires-Dist: pyside2 ; extra == 'pyside2'
Provides-Extra: pyside6
Requires-Dist: pyside6 ; extra == 'pyside6'
Provides-Extra: testing
Requires-Dist: tox ; extra == 'testing'
Requires-Dist: tox-conda ; extra == 'testing'
Requires-Dist: pytest ; extra == 'testing'
Requires-Dist: pytest-qt ; extra == 'testing'
Requires-Dist: pytest-cov ; extra == 'testing'
